geminix/__init__.py
geminix/model.py
geminix-0.0.1.dist-info/LICENSE
geminix-0.0.1.dist-info/WHEEL
geminix-0.0.1.dist-info/METADATA
geminix-0.0.1.dist-info/RECORD
